sklearn/multioutput.py
sklearn/isotonic.py
sklearn/multiclass.py
sklearn/_min_dependencies.py
sklearn/meson.build
sklearn/_config.py
sklearn/discriminant_analysis.py
sklearn/pipeline.py
sklearn/calibration.py
sklearn/conftest.py
sklearn/_isotonic.pyx
sklearn/random_projection.py
sklearn/_built_with_meson.py
sklearn/dummy.py
sklearn/base.py
sklearn/exceptions.py
sklearn/naive_bayes.py
sklearn/kernel_ridge.py
sklearn/_isotonic.cpython-39-x86_64-linux-gnu.so
sklearn/_distributor_init.py
sklearn/kernel_approximation.py
sklearn/__init__.py
sklearn/feature_selection/_base.py
sklearn/feature_selection/_univariate_selection.py
sklearn/feature_selection/_rfe.py
sklearn/feature_selection/_sequential.py
sklearn/feature_selection/_variance_threshold.py
sklearn/feature_selection/_mutual_info.py
sklearn/feature_selection/_from_model.py
sklearn/feature_selection/__init__.py
sklearn/feature_selection/tests/test_chi2.py
sklearn/feature_selection/tests/test_sequential.py
sklearn/feature_selection/tests/test_from_model.py
sklearn/feature_selection/tests/test_mutual_info.py
sklearn/feature_selection/tests/test_base.py
sklearn/feature_selection/tests/test_feature_select.py
sklearn/feature_selection/tests/test_variance_threshold.py
sklearn/feature_selection/tests/test_rfe.py
sklearn/feature_selection/tests/__init__.py
sklearn/model_selection/_plot.py
sklearn/model_selection/_validation.py
sklearn/model_selection/_search.py
sklearn/model_selection/_search_successive_halving.py
sklearn/model_selection/_split.py
sklearn/model_selection/_classification_threshold.py
sklearn/model_selection/__init__.py
sklearn/model_selection/tests/test_classification_threshold.py
sklearn/model_selection/tests/test_successive_halving.py
sklearn/model_selection/tests/test_search.py
sklearn/model_selection/tests/common.py
sklearn/model_selection/tests/test_plot.py
sklearn/model_selection/tests/test_split.py
sklearn/model_selection/tests/test_validation.py
scikit_lexicographical_trees-0.0.4.dist-info/WHEEL
scikit_lexicographical_trees-0.0.4.dist-info/RECORD
scikit_lexicographical_trees-0.0.4.dist-info/METADATA
