Metadata-Version: 2.1
Name: scikit-lexicographical-trees
Version: 0.0.4
Summary: A set of python modules for machine learning and data mining
Home-page: https://simonprovost.github.io/scikit-longitudinal/
Maintainer-Email: scikit-longitudinal-developpers <simon.gilbert.provost@gmail.com>
License: new BSD
Classifier: Intended Audience :: Science/Research
Classifier: Intended Audience :: Developers
Classifier: License :: OSI Approved :: BSD License
Classifier: Programming Language :: C
Classifier: Programming Language :: Python
Classifier: Topic :: Software Development
Classifier: Topic :: Scientific/Engineering
Classifier: Development Status :: 5 - Production/Stable
Classifier: Operating System :: Microsoft :: Windows
Classifier: Operating System :: POSIX
Classifier: Operating System :: Unix
Classifier: Operating System :: MacOS
Classifier: Programming Language :: Python :: 3
Classifier: Programming Language :: Python :: 3.9
Classifier: Programming Language :: Python :: 3.10
Classifier: Programming Language :: Python :: 3.11
Classifier: Programming Language :: Python :: 3.12
Classifier: Programming Language :: Python :: Implementation :: CPython
Project-URL: Homepage, https://simonprovost.github.io/scikit-longitudinal/
Project-URL: Source, https://github.com/simonprovost/scikit-lexicographical-trees
Project-URL: Download, https://pypi.org/project/scikit-lexicographical-trees/#files
Project-URL: Tracker, https://github.com/simonprovost/scikit-lexicographical-trees/issues
Project-URL: Release notes, https://github.com/simonprovost/scikit-longitudinal/releases
Requires-Python: >=3.9
Requires-Dist: numpy>=1.19.5
Requires-Dist: scipy>=1.6.0
Requires-Dist: joblib>=1.2.0
Requires-Dist: threadpoolctl>=3.1.0
Requires-Dist: numpy>=1.19.5; extra == "build"
Requires-Dist: scipy>=1.6.0; extra == "build"
Requires-Dist: cython>=3.0.10; extra == "build"
Requires-Dist: meson-python>=0.16.0; extra == "build"
Requires-Dist: numpy>=1.19.5; extra == "install"
Requires-Dist: scipy>=1.6.0; extra == "install"
Requires-Dist: joblib>=1.2.0; extra == "install"
Requires-Dist: threadpoolctl>=3.1.0; extra == "install"
Requires-Dist: matplotlib>=3.3.4; extra == "benchmark"
Requires-Dist: pandas>=1.1.5; extra == "benchmark"
Requires-Dist: memory_profiler>=0.57.0; extra == "benchmark"
Requires-Dist: matplotlib>=3.3.4; extra == "docs"
Requires-Dist: scikit-image>=0.17.2; extra == "docs"
Requires-Dist: pandas>=1.1.5; extra == "docs"
Requires-Dist: seaborn>=0.9.0; extra == "docs"
Requires-Dist: memory_profiler>=0.57.0; extra == "docs"
Requires-Dist: sphinx>=7.3.7; extra == "docs"
Requires-Dist: sphinx-copybutton>=0.5.2; extra == "docs"
Requires-Dist: sphinx-gallery>=0.16.0; extra == "docs"
Requires-Dist: numpydoc>=1.2.0; extra == "docs"
Requires-Dist: Pillow>=7.1.2; extra == "docs"
Requires-Dist: pooch>=1.6.0; extra == "docs"
Requires-Dist: sphinx-prompt>=1.4.0; extra == "docs"
Requires-Dist: sphinxext-opengraph>=0.9.1; extra == "docs"
Requires-Dist: plotly>=5.14.0; extra == "docs"
Requires-Dist: polars>=0.20.23; extra == "docs"
Requires-Dist: sphinx-design>=0.5.0; extra == "docs"
Requires-Dist: sphinxcontrib-sass>=0.3.4; extra == "docs"
Requires-Dist: pydata-sphinx-theme>=0.15.3; extra == "docs"
Requires-Dist: sphinx-remove-toctrees>=1.0.0.post1; extra == "docs"
Requires-Dist: matplotlib>=3.3.4; extra == "examples"
Requires-Dist: scikit-image>=0.17.2; extra == "examples"
Requires-Dist: pandas>=1.1.5; extra == "examples"
Requires-Dist: seaborn>=0.9.0; extra == "examples"
Requires-Dist: pooch>=1.6.0; extra == "examples"
Requires-Dist: plotly>=5.14.0; extra == "examples"
Requires-Dist: matplotlib>=3.3.4; extra == "tests"
Requires-Dist: scikit-image>=0.17.2; extra == "tests"
Requires-Dist: pandas>=1.1.5; extra == "tests"
Requires-Dist: pytest>=7.1.2; extra == "tests"
Requires-Dist: pytest-cov>=2.9.0; extra == "tests"
Requires-Dist: ruff>=0.2.1; extra == "tests"
Requires-Dist: black>=24.3.0; extra == "tests"
Requires-Dist: mypy>=1.9; extra == "tests"
Requires-Dist: pyamg>=4.0.0; extra == "tests"
Requires-Dist: polars>=0.20.23; extra == "tests"
Requires-Dist: pyarrow>=12.0.0; extra == "tests"
Requires-Dist: numpydoc>=1.2.0; extra == "tests"
Requires-Dist: pooch>=1.6.0; extra == "tests"
Requires-Dist: conda-lock==2.5.6; extra == "maintenance"
Provides-Extra: build
Provides-Extra: install
Provides-Extra: benchmark
Provides-Extra: docs
Provides-Extra: examples
Provides-Extra: tests
Provides-Extra: maintenance
